naver_sens_client/__init__.py
naver_sens_client/client.py
naver_sens_client-0.0.3.dist-info/LICENSE
naver_sens_client-0.0.3.dist-info/METADATA
naver_sens_client-0.0.3.dist-info/WHEEL
naver_sens_client-0.0.3.dist-info/top_level.txt
naver_sens_client-0.0.3.dist-info/RECORD
