Metadata-Version: 2.1
Name: naver-sens-client
Version: 0.0.3
Summary: NAVER SENS CLIENT
Home-page: https://github.com/santutu/NaverSensClient
Author: santutu
Author-email: santutu@naver.com
License: UNKNOWN
Platform: UNKNOWN
Classifier: Programming Language :: Python :: 3
Classifier: License :: OSI Approved :: MIT License
Classifier: Operating System :: OS Independent
